Metadata-Version: 1.0
Name: torrent-helper
Version: 1.3
Summary: CLI tool for torrent download
Home-page: https://github.com/prateekM59/torrent_helper
Author: Prateek Mahajan
Author-email: prateekmahajan59@gmail.com
License: MIT
Keywords: utorrent helper torrent helper CLI downloader windows
Platform: UNKNOWN
